README.md
setup.py
dsetnn/__init__.py
dsetnn.egg-info/PKG-INFO
dsetnn.egg-info/SOURCES.txt
dsetnn.egg-info/dependency_links.txt
dsetnn.egg-info/requires.txt
dsetnn.egg-info/top_level.txt